uipath_connectors/atlassian_jira/__init__.py
uipath_connectors/atlassian_jira/client.py
uipath_connectors/atlassian_jira/errors.py
uipath_connectors/atlassian_jira/py.typed
uipath_connectors/atlassian_jira/types.py
uipath_connectors/atlassian_jira/api/__init__.py
uipath_connectors/atlassian_jira/api/curated_add_comment/__init__.py
uipath_connectors/atlassian_jira/api/curated_add_comment/add_comment.py
uipath_connectors/atlassian_jira/api/curated_create_issue/__init__.py
uipath_connectors/atlassian_jira/api/curated_create_issue/create_issue.py
uipath_connectors/atlassian_jira/api/curated_download_issue_attachment/__init__.py
uipath_connectors/atlassian_jira/api/curated_download_issue_attachment/download_issue_attachment.py
uipath_connectors/atlassian_jira/api/curated_edit_issue/__init__.py
uipath_connectors/atlassian_jira/api/curated_edit_issue/upsert_issue.py
uipath_connectors/atlassian_jira/api/curated_get_issue/__init__.py
uipath_connectors/atlassian_jira/api/curated_get_issue/get_issue.py
uipath_connectors/atlassian_jira/api/curated_issue_assignee/__init__.py
uipath_connectors/atlassian_jira/api/curated_issue_assignee/update_issue_assignee.py
uipath_connectors/atlassian_jira/api/curated_issue_status_update/__init__.py
uipath_connectors/atlassian_jira/api/curated_issue_status_update/transition_issue.py
uipath_connectors/atlassian_jira/api/issue_attachments/__init__.py
uipath_connectors/atlassian_jira/api/issue_attachments/add_attachment.py
uipath_connectors/atlassian_jira/api/issue_comment/__init__.py
uipath_connectors/atlassian_jira/api/issue_comment/get_comments.py
uipath_connectors/atlassian_jira/api/issue_search_get/__init__.py
uipath_connectors/atlassian_jira/api/issue_search_get/search_issueby_jql.py
uipath_connectors/atlassian_jira/api/search_user/__init__.py
uipath_connectors/atlassian_jira/api/search_user/find_user_by_email.py
uipath_connectors/atlassian_jira/api/server_info/__init__.py
uipath_connectors_atlassian_jira-1.6.14.dev12.dist-info/METADATA
uipath_connectors_atlassian_jira-1.6.14.dev12.dist-info/WHEEL
uipath_connectors_atlassian_jira-1.6.14.dev12.dist-info/entry_points.txt
uipath_connectors_atlassian_jira-1.6.14.dev12.dist-info/top_level.txt
uipath_connectors_atlassian_jira-1.6.14.dev12.dist-info/RECORD
